{
    "appid": "1040730",
    "type": "Game",
    "name": "ZUSI 3 - Aerosoft Edition",
    "schinese_name": "",
    "isfreeapp": "0",
    "change_number": "27259257",
    "update_time": "2025-02-01 02:31:35",
    "depot": {
        "228990": {
            "config": {
                "oslist": "windows"
            },
            "depotfromapp": "228980",
            "sharedinstall": "1"
        },
        "1040731": {
            "manifests": {
                "public": {
                    "gid": "4540705946811300972",
                    "size": "10556232386",
                    "download": "3035684112"
                }
            },
            "decryptionkey": "c5b3b28e4505b43631d0f7d2f350534de914ecf27c9b27517622c56b767dc1d1"
        },
        "branches": {
            "public": {
                "buildid": "16863621",
                "timeupdated": "1735801165"
            }
        }
    }
}