{
    "appid": "1074620",
    "type": "Game",
    "name": "Adore",
    "schinese_name": "",
    "isfreeapp": "0",
    "change_number": "27338524",
    "update_time": "2025-02-06 12:17:57",
    "depot": {
        "1074621": {
            "config": {
                "oslist": "windows"
            },
            "manifests": {
                "public": {
                    "gid": "1659284166764556920",
                    "size": "2563493554",
                    "download": "719535232"
                }
            },
            "decryptionkey": "06b91ae89d2ff648eb674e715415a9782cae0cc2325e17d0f70116da94564ce4"
        },
        "branches": {
            "public": {
                "buildid": "12632545",
                "timeupdated": "1701277394"
            }
        },
        "privatebranches": "1"
    }
}