{
    "appid": "1194810",
    "type": "Game",
    "name": "Meet Your Maker",
    "schinese_name": "",
    "isfreeapp": "0",
    "change_number": "26900250",
    "update_time": "2025-01-08 08:18:46",
    "depot": {
        "228989": {
            "config": {
                "oslist": "windows"
            },
            "depotfromapp": "228980",
            "sharedinstall": "1"
        },
        "228990": {
            "config": {
                "oslist": "windows"
            },
            "depotfromapp": "228980",
            "sharedinstall": "1"
        },
        "1194811": {
            "manifests": {
                "public": {
                    "gid": "8517663937155301514",
                    "size": "16477385654",
                    "download": "15623371072"
                }
            },
            "decryptionkey": "17f8c8a9b91c20321eab82f296993f16e3ad089ab4d2a51016ba67ec875004a5"
        },
        "branches": {
            "public": {
                "buildid": "16010694",
                "timeupdated": "1729179336"
            }
        },
        "privatebranches": "1"
    }
}