{
    "appid": "1332340",
    "type": "Game",
    "name": "DISORDER",
    "schinese_name": "",
    "isfreeapp": "0",
    "change_number": "27988749",
    "update_time": "2025-03-17 15:08:14",
    "depot": {
        "228989": {
            "config": {
                "oslist": "windows"
            },
            "depotfromapp": "228980",
            "sharedinstall": "1"
        },
        "228990": {
            "config": {
                "oslist": "windows"
            },
            "depotfromapp": "228980",
            "sharedinstall": "1"
        },
        "1332341파이터 ": {
            "config": {
                "oslist": "windows",
                "language": ""
            }
        },
        "1332341": {
            "config": {
                "oslist": "windows"
            },
            "manifests": {
                "public": {
                    "gid": "8611191480380001662",
                    "size": "14485493138",
                    "download": "14261298416"
                }
            },
            "decryptionkey": "4299a87965c6fa8f20880c1225607076c95cae50666d2ee56b9a19d5cc3e7da2"
        },
        "branches": {
            "public": {
                "buildid": "17588359",
                "timeupdated": "1741097933"
            }
        },
        "privatebranches": "1"
    }
}