{
    "appid": "1384700",
    "type": "Game",
    "name": "A Gay Love Story About Gay Love",
    "schinese_name": "",
    "isfreeapp": "0",
    "change_number": "26950037",
    "update_time": "2025-01-11 08:17:10",
    "depot": {
        "1384701": {
            "manifests": {
                "public": {
                    "gid": "3362301526426793186",
                    "size": "166484205",
                    "download": "151035840"
                }
            },
            "decryptionkey": "e56ce9e9d1f431d099186c05e959e157ea193e161922b181824f842dcc8e4c0e"
        },
        "branches": {
            "public": {
                "buildid": "5766633",
                "timeupdated": "1604178876"
            }
        },
        "privatebranches": "1"
    }
}