{
    "appid": "1387580",
    "type": "Game",
    "name": "AbsentedAge:アブセンテッドエイジ ～亡霊少女のローグライクアクションSRPG -幽玄の章-",
    "schinese_name": "AbsentedAge: 亡灵少女的方格世界",
    "isfreeapp": "0",
    "change_number": "27416272",
    "update_time": "2025-02-11 16:42:32",
    "depot": {
        "baselanguages": "japanese",
        "1387581": {
            "config": {
                "oslist": "windows",
                "osarch": "64",
                "language": ""
            },
            "manifests": {
                "public": {
                    "gid": "3014509403547888904",
                    "size": "418159541",
                    "download": "242818512"
                }
            },
            "decryptionkey": "492517975f2c091157702d1e117764e3dd52cab29a7f678123595de45af6f4b3"
        },
        "1387582": {
            "config": {
                "oslist": "windows",
                "osarch": "32",
                "language": ""
            },
            "manifests": {
                "public": {
                    "gid": "3926253116829454596",
                    "size": "392112047",
                    "download": "240226272"
                }
            },
            "decryptionkey": ""
        },
        "branches": {
            "public": {
                "buildid": "17318357",
                "timeupdated": "1739263343"
            }
        }
    }
}