{
    "appid": "1564110",
    "type": "Game",
    "name": "Beside Myself",
    "schinese_name": "",
    "isfreeapp": "0",
    "change_number": "25550151",
    "update_time": "2024-10-06 03:09:51",
    "depot": {
        "228988": {
            "config": {
                "oslist": "windows"
            },
            "depotfromapp": "228980",
            "sharedinstall": "1"
        },
        "228990": {
            "config": {
                "oslist": "windows"
            },
            "depotfromapp": "228980",
            "sharedinstall": "1"
        },
        "1564111": {
            "config": {
                "oslist": "windows"
            },
            "manifests": {
                "public": {
                    "gid": "1250746830043258599",
                    "size": "10324631937",
                    "download": "4792936064"
                }
            },
            "decryptionkey": "cb428960ccf85418ae7e450fb649f914af50688e45ce9d53dd815a7c297f30c4"
        },
        "baselanguages": "english",
        "branches": {
            "public": {
                "buildid": "7641589",
                "timeupdated": "1635843138"
            }
        }
    }
}