{
    "appid": "1705180",
    "type": "Game",
    "name": "Gunner, HEAT, PC!",
    "schinese_name": "",
    "isfreeapp": "0",
    "change_number": "28256783",
    "update_time": "2025-04-02 05:33:31",
    "depot": {
        "1705181": {
            "manifests": {
                "public": {
                    "gid": "2990332996982464125",
                    "size": "9104626232",
                    "download": "2830532944"
                }
            },
            "decryptionkey": "9dba2a78017b5384c4cc0cf599c6b3fe252c3635dcef818c04f98aa9ea9374e9"
        },
        "branches": {
            "public": {
                "buildid": "17945785",
                "timeupdated": "1743543206"
            }
        }
    }
}