{
    "appid": "1748390",
    "type": "Game",
    "name": "Rocket Bot Royale",
    "schinese_name": "",
    "isfreeapp": "0",
    "change_number": "27964445",
    "update_time": "2025-03-15 04:18:19",
    "depot": {
        "1748391": {
            "manifests": {
                "public": {
                    "gid": "8835268404542250565",
                    "size": "60",
                    "download": "112"
                }
            },
            "decryptionkey": "584daa2a12961d9e4c190ee5f59596e20ece2b52e55fbb6c0e828fc6d435e413"
        },
        "1748392": {
            "config": {
                "oslist": "windows"
            },
            "manifests": {
                "public": {
                    "gid": "5018300563316588335",
                    "size": "70369080",
                    "download": "31105728"
                }
            },
            "decryptionkey": "52d7226294898dfff7be38d80856f239d24a241c338dd3c0534845adeb3ed943"
        },
        "1748393": {
            "config": {
                "oslist": "macos"
            },
            "manifests": {
                "public": {
                    "gid": "1885847799899630999",
                    "size": "79411092",
                    "download": "33185088"
                }
            },
            "decryptionkey": ""
        },
        "1748394": {
            "config": {
                "oslist": "linux"
            },
            "manifests": {
                "public": {
                    "gid": "3367650137510762019",
                    "size": "77709256",
                    "download": "33175232"
                }
            },
            "decryptionkey": ""
        },
        "branches": {
            "public": {
                "buildid": "17730927",
                "timeupdated": "1741983471"
            }
        },
        "privatebranches": "1"
    }
}