{
    "appid": "1865960",
    "type": "Game",
    "name": "Symphonia",
    "schinese_name": "",
    "isfreeapp": "0",
    "change_number": "28548918",
    "update_time": "2025-04-18 20:04:30",
    "depot": {
        "1865961": {
            "manifests": {
                "public": {
                    "gid": "8204072014340868330",
                    "size": "4082742470",
                    "download": "1177048720"
                }
            },
            "decryptionkey": "dbc805144c65b0d9d7e0894a0065ec39573d8f77c3e96581a2007755bb9e5b68"
        },
        "branches": {
            "public": {
                "buildid": "17356667",
                "timeupdated": "1739524544"
            }
        },
        "privatebranches": "1"
    }
}