{
    "appid": "1950450",
    "type": "Game",
    "name": "Loop Queen-Escape Dungeon 3",
    "schinese_name": "Loop Queen-地牢脱出3 轮回女王",
    "isfreeapp": "0",
    "change_number": "28375427",
    "update_time": "2025-04-09 07:02:38",
    "depot": {
        "hasdepotsindlc": "0",
        "1950451": {
            "config": {
                "oslist": "windows",
                "osarch": "64"
            },
            "manifests": {
                "public": {
                    "gid": "6856399044633230278",
                    "size": "3437761691",
                    "download": "977449584"
                }
            },
            "decryptionkey": "1ffccddc2535c02d22b5227b4c7297e8eafeae544af23ba786b112d8de379811"
        },
        "1950452": {
            "config": {
                "oslist": "macos",
                "osarch": "64"
            },
            "manifests": {
                "public": {
                    "gid": "8560545174038051634",
                    "size": "3462669022",
                    "download": "985670736"
                }
            },
            "decryptionkey": "cb2d3980bec0b5e23080bf43d039ad9000204d325e08c7da64487f8a05533530"
        },
        "1950453": {
            "config": {
                "oslist": "windows",
                "osarch": "64"
            },
            "manifests": {
                "public": {
                    "gid": "3983862157727539385",
                    "size": "3437761691",
                    "download": "977334784"
                }
            },
            "decryptionkey": ""
        },
        "branches": {
            "public": {
                "buildid": "16136891",
                "timeupdated": "1729603382"
            }
        }
    }
}