{
    "appid": "2055360",
    "type": "Game",
    "name": "The Zebra-Man!",
    "schinese_name": "",
    "isfreeapp": "0",
    "change_number": "27984532",
    "update_time": "2025-03-17 05:55:45",
    "depot": {
        "2055361": {
            "manifests": {
                "public": {
                    "gid": "5160747022771203912",
                    "size": "924482679",
                    "download": "845847600"
                }
            },
            "decryptionkey": "19f342a8497bf28de6b8fbc0326f90065ed36bfc379926bc1978f2dfc673857c"
        },
        "branches": {
            "public": {
                "buildid": "17253375",
                "timeupdated": "1738930732"
            }
        },
        "privatebranches": "1"
    }
}