{
    "appid": "2257590",
    "type": "Game",
    "name": "Alien Agent X",
    "schinese_name": "异星特工X",
    "isfreeapp": "0",
    "change_number": "28093417",
    "update_time": "2025-03-23 13:19:42",
    "depot": {
        "228989": {
            "config": {
                "oslist": "windows"
            },
            "depotfromapp": "228980",
            "sharedinstall": "1"
        },
        "228990": {
            "config": {
                "oslist": "windows"
            },
            "depotfromapp": "228980",
            "sharedinstall": "1"
        },
        "229007": {
            "config": {
                "oslist": "windows"
            },
            "depotfromapp": "228980",
            "sharedinstall": "1"
        },
        "229012": {
            "config": {
                "oslist": "windows"
            },
            "depotfromapp": "228980",
            "sharedinstall": "1"
        },
        "229020": {
            "config": {
                "oslist": "windows"
            },
            "depotfromapp": "228980",
            "sharedinstall": "1"
        },
        "229033": {
            "config": {
                "oslist": "windows"
            },
            "depotfromapp": "228980",
            "sharedinstall": "1"
        },
        "2257591": {
            "config": {
                "oslist": "windows",
                "osarch": "64"
            },
            "manifests": {
                "public": {
                    "gid": "1299414548508964649",
                    "size": "4942241629",
                    "download": "4412859280"
                }
            },
            "decryptionkey": "6030654899eb4963856f04bedf210c64d290ede42c7caac7bf0cd434c5a988bc"
        },
        "branches": {
            "public": {
                "buildid": "15810346",
                "timeupdated": "1733983898"
            }
        }
    }
}