{
    "appid": "2264090",
    "type": "Game",
    "name": "Desktop Garage Kit",
    "schinese_name": "桌面手办",
    "isfreeapp": "0",
    "change_number": "27962617",
    "update_time": "2025-03-15 02:14:35",
    "depot": {
        "hasdepotsindlc": "0",
        "2264091": {
            "config": {
                "oslist": "windows",
                "osarch": "64"
            },
            "manifests": {
                "public": {
                    "gid": "6062336372499525134",
                    "size": "24285814165",
                    "download": "6867338944"
                }
            },
            "decryptionkey": "09fe8b6d4e4e72ffcc2c1a7c5350e441eb9792badeed8568f1891cd7f5b60f14"
        },
        "2264092": {
            "config": {
                "oslist": "macos"
            },
            "manifests": {
                "public": {
                    "gid": "3219000967167973436",
                    "size": "2612228820",
                    "download": "514568592"
                }
            },
            "decryptionkey": ""
        },
        "branches": {
            "public": {
                "buildid": "17729600",
                "timeupdated": "1741976067"
            }
        }
    }
}