{
    "appid": "2649800",
    "type": "Game",
    "name": "Vinecard",
    "schinese_name": "唐草卡 Vinecard",
    "isfreeapp": "0",
    "change_number": "28076126",
    "update_time": "2025-03-22 00:29:45",
    "depot": {
        "2649801": {
            "manifests": {
                "public": {
                    "gid": "3148000429582944473",
                    "size": "5614911742",
                    "download": "963071072"
                }
            },
            "decryptionkey": "9684e996016beca183f204ee7259982a0db5674359252e46dc60f16ecac407f5"
        },
        "baselanguages": "english,schinese,tchinese",
        "branches": {
            "public": {
                "buildid": "17811796",
                "timeupdated": "1742574575"
            }
        },
        "privatebranches": "1"
    }
}