{
    "appid": "272600",
    "type": "Game",
    "name": "Detective Grimoire",
    "schinese_name": "",
    "isfreeapp": "0",
    "change_number": "27138944",
    "update_time": "2025-01-24 06:26:12",
    "depot": {
        "overridescddb": "1",
        "272601": {
            "systemdefined": "1",
            "config": {
                "oslist": "windows"
            },
            "manifests": {
                "public": {
                    "gid": "4581539050612241924",
                    "size": "161534607",
                    "download": "132428192"
                }
            },
            "decryptionkey": "2553865c63c28d59cffeeb360b4bb5cf2ad50101d5dc706048e1948d53f22758"
        },
        "272602": {
            "config": {
                "oslist": "macos"
            },
            "manifests": {
                "public": {
                    "gid": "2618419603341048346",
                    "size": "292159642",
                    "download": "133917280"
                }
            },
            "decryptionkey": ""
        },
        "272603": {
            "config": {
                "oslist": "linux"
            },
            "manifests": {
                "public": {
                    "gid": "8253097573333876722",
                    "size": "163186556",
                    "download": "129672944"
                }
            },
            "decryptionkey": ""
        },
        "branches": {
            "public": {
                "buildid": "890170"
            }
        },
        "privatebranches": "1"
    }
}