{
    "appid": "3035500",
    "type": "Game",
    "name": "Fantasy Map Simulator",
    "schinese_name": "架空地图模拟器",
    "isfreeapp": "0",
    "change_number": "28245389",
    "update_time": "2025-04-01 17:40:45",
    "depot": {
        "228989": {
            "config": {
                "oslist": "windows"
            },
            "depotfromapp": "228980",
            "sharedinstall": "1"
        },
        "3035501": {
            "manifests": {
                "public": {
                    "gid": "4531860766397851980",
                    "size": "678668721",
                    "download": "234722896"
                },
                "public-beta": {
                    "gid": "4531860766397851980",
                    "size": "678668721",
                    "download": "234722896"
                }
            },
            "decryptionkey": "94673b1ae3605b9caf7d167097a8ff459dde31b918ffd8d5c85f2187001485d4"
        },
        "baselanguages": "english,german,french,koreana,spanish,schinese,tchinese,russian,japanese,portuguese,polish,turkish,brazilian,latam",
        "workshopdepot": "3035500",
        "branches": {
            "public": {
                "buildid": "17934269",
                "timeupdated": "1743483235"
            },
            "public-beta": {
                "buildid": "17934269",
                "description": "public 测试",
                "timeupdated": "1743482874"
            }
        },
        "privatebranches": "1",
        "workshopdepotdecryptionkey": ""
    }
}