{
    "appid": "3037090",
    "type": "Demo",
    "name": "Storage Hunter Simulator Demo",
    "schinese_name": "",
    "isfreeapp": "0",
    "change_number": "27933121",
    "update_time": "2025-03-13 20:51:25",
    "depot": {
        "228989": {
            "config": {
                "oslist": "windows"
            },
            "depotfromapp": "228980",
            "sharedinstall": "1"
        },
        "228990": {
            "config": {
                "oslist": "windows"
            },
            "depotfromapp": "228980",
            "sharedinstall": "1"
        },
        "3037091": {
            "manifests": {
                "public": {
                    "gid": "7295191439245809231",
                    "size": "10105993509",
                    "download": "7941704080"
                }
            }
        },
        "branches": {
            "public": {
                "buildid": "16549937",
                "timeupdated": "1732730276"
            }
        },
        "privatebranches": "1"
    }
}