{
    "appid": "3083280",
    "type": "Demo",
    "name": "Kebabstar Demo",
    "schinese_name": "",
    "isfreeapp": "0",
    "change_number": "26152362",
    "update_time": "2024-11-12 14:49:35",
    "depot": {
        "228989": {
            "config": {
                "oslist": "windows"
            },
            "depotfromapp": "228980",
            "sharedinstall": "1"
        },
        "228990": {
            "config": {
                "oslist": "windows"
            },
            "depotfromapp": "228980",
            "sharedinstall": "1"
        },
        "3083281": {
            "manifests": {
                "public": {
                    "gid": "5564141734886368422",
                    "size": "4196596126",
                    "download": "3705789072"
                }
            },
            "decryptionkey": "01fa213516d5514f220a5267d452beacded8604fd316337845da7f5868979664"
        },
        "branches": {
            "public": {
                "buildid": "16374652",
                "timeupdated": "1731394172"
            }
        }
    }
}