{
    "appid": "3135900",
    "type": "Game",
    "name": "Dawn of Survivor",
    "schinese_name": "幸存者的黎明",
    "isfreeapp": "0",
    "change_number": "26910455",
    "update_time": "2025-01-09 00:17:35",
    "depot": {
        "3135901": {
            "manifests": {
                "public": {
                    "gid": "2690466850198022859",
                    "size": "1141100373",
                    "download": "305663136"
                }
            },
            "decryptionkey": "313f70203f1dd8f45d21c130f90cb577a53dbeaba71bc4d0433af004cce30093"
        },
        "branches": {
            "public": {
                "buildid": "16941475",
                "timeupdated": "1736353013"
            }
        }
    }
}