{
    "appid": "3140620",
    "type": "Game",
    "name": "C.A.S.T.",
    "schinese_name": "",
    "isfreeapp": "0",
    "change_number": "28249044",
    "update_time": "2025-04-01 21:21:51",
    "depot": {
        "3140621": {
            "manifests": {
                "public": {
                    "gid": "1331472876722866944",
                    "size": "2376304237",
                    "download": "671003040"
                }
            },
            "decryptionkey": "6b666c3790c092f34983d87895ab3adc087fc195a6eafe8cd3c85ac64f26636c"
        },
        "branches": {
            "public": {
                "buildid": "17692190",
                "timeupdated": "1741781275"
            }
        },
        "privatebranches": "1"
    }
}