{
    "appid": "548330",
    "type": "Game",
    "name": "Wheely",
    "schinese_name": "",
    "isfreeapp": "0",
    "change_number": "25842933",
    "update_time": "2024-10-23 01:06:17",
    "depot": {
        "548331": {
            "config": {
                "oslist": "windows"
            },
            "manifests": {
                "public": {
                    "gid": "2071032348136774956",
                    "size": "146685603",
                    "download": "124141936"
                }
            },
            "decryptionkey": "de6cecca9a4d203d9abdd4a4f93935507c202bb0e3d2b234d0284f62fc24c76d"
        },
        "baselanguages": "english,german,french,spanish,russian,portuguese,ukrainian",
        "branches": {
            "public": {
                "buildid": "1533968",
                "timeupdated": "1482334094"
            }
        }
    }
}