{
    "appid": "677340",
    "type": "Game",
    "name": "The Colonists",
    "schinese_name": "殖民者",
    "isfreeapp": "0",
    "change_number": "28238887",
    "update_time": "2025-04-01 08:43:51",
    "depot": {
        "workshopdepot": "677340",
        "677341": {
            "config": {
                "oslist": "windows"
            },
            "manifests": {
                "public": {
                    "gid": "6770101054423775486",
                    "size": "893250808",
                    "download": "329815248"
                },
                "development": {
                    "gid": "8728992410817081483",
                    "size": "921679287",
                    "download": "336922176"
                },
                "review": {
                    "gid": "6770101054423775486",
                    "size": "893250808",
                    "download": "329815248"
                },
                "v1.6.14": {
                    "gid": "8632081931032329320",
                    "size": "759678616",
                    "download": "291661872"
                },
                "v1.9.5.1": {
                    "gid": "6400471271403888185",
                    "size": "888073831",
                    "download": "327364256"
                }
            },
            "decryptionkey": "3d7728de928df3197a32149676017b26ef9e1222f52626fb2f19f3190a7e9433"
        },
        "677342": {
            "config": {
                "oslist": "macos"
            },
            "manifests": {
                "public": {
                    "gid": "7228892173481883263",
                    "size": "929965884",
                    "download": "342600128"
                },
                "development": {
                    "gid": "7228892173481883263",
                    "size": "929965884",
                    "download": "342600128"
                },
                "review": {
                    "gid": "7228892173481883263",
                    "size": "929965884",
                    "download": "342600128"
                },
                "v1.6.14": {
                    "gid": "4647520566175148666",
                    "size": "781623067",
                    "download": "298016976"
                },
                "v1.9.5.1": {
                    "gid": "2348107677790031076",
                    "size": "924017689",
                    "download": "339932592"
                }
            },
            "decryptionkey": ""
        },
        "677343": {
            "config": {
                "oslist": "linux"
            },
            "manifests": {
                "public": {
                    "gid": "9133671194066733304",
                    "size": "912989845",
                    "download": "328186960"
                },
                "development": {
                    "gid": "9133671194066733304",
                    "size": "912989845",
                    "download": "328186960"
                },
                "review": {
                    "gid": "9133671194066733304",
                    "size": "912989845",
                    "download": "328186960"
                },
                "v1.6.14": {
                    "gid": "5375393842313911543",
                    "size": "804838597",
                    "download": "293784656"
                },
                "v1.9.5.1": {
                    "gid": "4767899199894361550",
                    "size": "909259255",
                    "download": "326247984"
                }
            },
            "decryptionkey": ""
        },
        "2784480": {
            "dlcappid": "2784480"
        },
        "branches": {
            "public": {
                "buildid": "17932072",
                "timeupdated": "1743467247"
            },
            "development": {
                "buildid": "17932365",
                "timeupdated": "1743468227"
            },
            "review": {
                "buildid": "17932072",
                "timeupdated": "1743467213"
            },
            "v1.6.14": {
                "buildid": "13607331",
                "description": "v1.6.14",
                "timeupdated": "1718061946"
            },
            "v1.9.5.1": {
                "buildid": "15893156",
                "description": "v1.9.5.1",
                "timeupdated": "1731339709"
            }
        },
        "privatebranches": "1",
        "workshopdepotdecryptionkey": "13f3fcd06bf79baf372a433e9995719a6a89e090b95edfdeb6112a9297564339"
    }
}