{
    "appid": "856890",
    "type": "Game",
    "name": "JUSTICE SUCKS",
    "schinese_name": "",
    "isfreeapp": "0",
    "change_number": "26207888",
    "update_time": "2024-11-15 16:24:27",
    "depot": {
        "856891": {
            "config": {
                "oslist": "windows"
            },
            "manifests": {
                "public": {
                    "gid": "8356814732581836164",
                    "size": "2093892079",
                    "download": "1204917792"
                }
            },
            "decryptionkey": "255a38e3e742499a0e973be0b6cbde54cf7340ff6669fdc0112d3c0d1ae033e7"
        },
        "branches": {
            "public": {
                "buildid": "10467942",
                "timeupdated": "1676562580"
            }
        },
        "privatebranches": "1"
    }
}