{
    "appid": "946770",
    "type": "Game",
    "name": "Scheming Through The Zombie Apocalypse Ep2: Caged",
    "schinese_name": "",
    "isfreeapp": "0",
    "change_number": "28175376",
    "update_time": "2025-03-28 01:16:17",
    "depot": {
        "946771": {
            "config": {
                "oslist": "windows"
            },
            "manifests": {
                "public": {
                    "gid": "8457496819902256772",
                    "size": "1488255676",
                    "download": "354201360"
                }
            },
            "decryptionkey": "a59876f41082585993533644a4488a09906de8bec7d619409ab3bd4f4a20ef2c"
        },
        "946772": {
            "config": {
                "oslist": "macos"
            },
            "manifests": {
                "public": {
                    "gid": "4875142068898982219",
                    "size": "1530898269",
                    "download": "366478688"
                }
            },
            "decryptionkey": ""
        },
        "branches": {
            "public": {
                "buildid": "17700423",
                "timeupdated": "1741821793"
            }
        }
    }
}